[
  {
    "roomNumber": "P101",
    "name": "Phòng trọ số 101",
    "title": "Phòng trọ cao cấp gần trung tâm",
    "description": "Phòng rộng rãi, đầy đủ tiện nghi, an ninh tốt. Gần chợ, siêu thị, trường học. Phù hợp cho sinh viên, công nhân.",
    "price": 3500000,
    "area": 25.5,
    "bedrooms": 1,
    "bathrooms": 1,
    "address": "123 Đường Nguyễn Văn Linh",
    "district": "Quận 7",
    "city": "TP. Hồ Chí Minh",
    "ward": "Phường Tân Phong",
    "amenities": ["Wifi", "Điều hòa", "Máy nước nóng", "Tủ lạnh", "Máy giặt", "Bảo vệ 24/7"],
    "images": [
      "https://example.com/images/room101-1.jpg",
      "https://example.com/images/room101-2.jpg"
    ],
    "status": "AVAILABLE",
    "isActive": true,
    "capacity": 2,
    "direction": "Đông Nam",
    "floor": 3,
    "hasElevator": true,
    "hasParking": true,
    "createdAt": "2025-11-20T10:00:00",
    "updatedAt": "2025-11-20T10:00:00"
  },
  {
    "roomNumber": "P102",
    "name": "Phòng trọ số 102",
    "title": "Phòng trọ giá rẻ cho sinh viên",
    "description": "Phòng nhỏ gọn, giá cả phải chăng, phù hợp cho sinh viên. Có đầy đủ tiện nghi cơ bản.",
    "price": 2000000,
    "area": 15.0,
    "bedrooms": 1,
    "bathrooms": 1,
    "address": "456 Đường Lê Văn Việt",
    "district": "Quận 9",
    "city": "TP. Hồ Chí Minh",
    "ward": "Phường Hiệp Phú",
    "amenities": ["Wifi", "Quạt", "Máy nước nóng"],
    "images": [
      "https://example.com/images/room102-1.jpg"
    ],
    "status": "AVAILABLE",
    "isActive": true,
    "capacity": 1,
    "direction": "Tây",
    "floor": 2,
    "hasElevator": false,
    "hasParking": true,
    "createdAt": "2025-11-20T10:00:00",
    "updatedAt": "2025-11-20T10:00:00"
  },
  {
    "roomNumber": "P201",
    "name": "Phòng trọ số 201",
    "title": "Phòng trọ view đẹp, yên tĩnh",
    "description": "Phòng view đẹp, yên tĩnh, phù hợp cho người làm việc tại nhà. Có ban công rộng.",
    "price": 4000000,
    "area": 30.0,
    "bedrooms": 2,
    "bathrooms": 1,
    "address": "789 Đường Võ Văn Tần",
    "district": "Quận 3",
    "city": "TP. Hồ Chí Minh",
    "ward": "Phường Võ Thị Sáu",
    "amenities": ["Wifi", "Điều hòa", "Máy nước nóng", "Tủ lạnh", "Máy giặt", "Ban công"],
    "images": [
      "https://example.com/images/room201-1.jpg",
      "https://example.com/images/room201-2.jpg",
      "https://example.com/images/room201-3.jpg"
    ],
    "status": "OCCUPIED",
    "isActive": true,
    "capacity": 3,
    "direction": "Nam",
    "floor": 2,
    "hasElevator": true,
    "hasParking": true,
    "createdAt": "2025-11-15T10:00:00",
    "updatedAt": "2025-11-20T10:00:00"
  },
  {
    "roomNumber": "P301",
    "name": "Phòng trọ số 301",
    "title": "Phòng trọ studio hiện đại",
    "description": "Phòng studio hiện đại, thiết kế đẹp, đầy đủ tiện nghi. Phù hợp cho cặp đôi hoặc người độc thân.",
    "price": 4500000,
    "area": 28.0,
    "bedrooms": 1,
    "bathrooms": 1,
    "address": "321 Đường Điện Biên Phủ",
    "district": "Quận Bình Thạnh",
    "city": "TP. Hồ Chí Minh",
    "ward": "Phường 25",
    "amenities": ["Wifi", "Điều hòa", "Máy nước nóng", "Tủ lạnh", "Máy giặt", "Bếp", "Bảo vệ 24/7"],
    "images": [
      "https://example.com/images/room301-1.jpg",
      "https://example.com/images/room301-2.jpg"
    ],
    "status": "AVAILABLE",
    "isActive": true,
    "capacity": 2,
    "direction": "Đông",
    "floor": 3,
    "hasElevator": true,
    "hasParking": true,
    "createdAt": "2025-11-18T10:00:00",
    "updatedAt": "2025-11-20T10:00:00"
  },
  {
    "roomNumber": "P401",
    "name": "Phòng trọ số 401",
    "title": "Phòng trọ giá rẻ, gần trường",
    "description": "Phòng giá rẻ, gần các trường đại học, phù hợp cho sinh viên. Có wifi miễn phí.",
    "price": 1800000,
    "area": 12.0,
    "bedrooms": 1,
    "bathrooms": 1,
    "address": "654 Đường Hoàng Diệu",
    "district": "Quận 4",
    "city": "TP. Hồ Chí Minh",
    "ward": "Phường 6",
    "amenities": ["Wifi", "Quạt", "Máy nước nóng"],
    "images": [
      "https://example.com/images/room401-1.jpg"
    ],
    "status": "AVAILABLE",
    "isActive": true,
    "capacity": 1,
    "direction": "Bắc",
    "floor": 4,
    "hasElevator": false,
    "hasParking": false,
    "createdAt": "2025-11-19T10:00:00",
    "updatedAt": "2025-11-20T10:00:00"
  }
]

